concoursetools/__init__.py
concoursetools/__main__.py
concoursetools/additional.py
concoursetools/colour.py
concoursetools/dockertools.py
concoursetools/importing.py
concoursetools/metadata.py
concoursetools/mocking.py
concoursetools/parsing.py
concoursetools/py.typed
concoursetools/resource.py
concoursetools/testing.py
concoursetools/typing.py
concoursetools/version.py
concoursetools/cli/__init__.py
concoursetools/cli/commands.py
concoursetools/cli/docstring.py
concoursetools/cli/parser.py
concoursetools-0.8.1.dist-info/licenses/LICENSE.md
concoursetools-0.8.1.dist-info/METADATA
concoursetools-0.8.1.dist-info/WHEEL
concoursetools-0.8.1.dist-info/top_level.txt
concoursetools-0.8.1.dist-info/RECORD
