Metadata-Version: 2.4
Name: concoursetools
Version: 0.8.1
Summary: Easily create Concourse resource types in Python.
Author-email: GCHQ <oss@gchq.gov.uk>
License: Apache License 2.0
Project-URL: Homepage, https://github.com/gchq/ConcourseTools/
Project-URL: Documentation, https://concoursetools.readthedocs.io/en/stable/
Project-URL: Repository, https://github.com/gchq/ConcourseTools/
Project-URL: Bug Tracker, https://github.com/gchq/ConcourseTools/issues
Project-URL: Changelog, https://concoursetools.readthedocs.io/en/latest/whats_new.html
Keywords: concourse,ci,cd
Classifier: Development Status :: 4 - Beta
Classifier: Intended Audience :: Developers
Classifier: License :: OSI Approved :: Apache Software License
Classifier: Natural Language :: English
Classifier: Programming Language :: Python :: 3.10
Classifier: Programming Language :: Python :: 3.11
Classifier: Programming Language :: Python :: 3.12
Classifier: Programming Language :: Python :: 3.13
Classifier: Programming Language :: Python :: 3.14
Classifier: Topic :: Software Development
Classifier: Typing :: Typed
Requires-Python: >=3.10
License-File: LICENSE.md
Dynamic: license-file
